[{"title": "IT System Development", "link": "https://www.jobstreet.co.id/id/job/it-system-development-3815026?jobId=jobstreet-id-job-3815026&sectionRank=2011&token=0~357b46f9-3b28-40ef-b670-614aaa1640ef&fr=SRP%20Job%20Listing", "qualified": []}, {"title": "Experienced Java Developer", "link": "https://www.jobstreet.co.id/id/job/experienced-java-developer-3822325?jobId=jobstreet-id-job-3822325&sectionRank=2012&token=0~357b46f9-3b28-40ef-b670-614aaa1640ef&fr=SRP%20Job%20Listing", "qualified": []}, {"title": ".NET Developer", "link": "https://www.jobstreet.co.id/id/job/.net-developer-3839808?jobId=jobstreet-id-job-3839808&sectionRank=2013&token=0~357b46f9-3b28-40ef-b670-614aaa1640ef&fr=SRP%20Job%20Listing", "qualified": []}, {"title": "Experienced Frontend Software Engineer", "link": "https://www.jobstreet.co.id/id/job/experienced-frontend-software-engineer-3835235?jobId=jobstreet-id-job-3835235&sectionRank=2014&token=0~357b46f9-3b28-40ef-b670-614aaa1640ef&fr=SRP%20Job%20Listing", "qualified": []}, {"title": "Product Owner", "link": "https://www.jobstreet.co.id/id/job/product-owner-3835510?jobId=jobstreet-id-job-3835510&sectionRank=2015&token=0~357b46f9-3b28-40ef-b670-614aaa1640ef&fr=SRP%20Job%20Listing", "qualified": []}, {"title": "SAP ERP", "link": "https://www.jobstreet.co.id/id/job/sap-erp-3836374?jobId=jobstreet-id-job-3836374&sectionRank=2016&token=0~357b46f9-3b28-40ef-b670-614aaa1640ef&fr=SRP%20Job%20Listing", "qualified": []}, {"title": "SAP SD Consultant", "link": "https://www.jobstreet.co.id/id/job/sap-sd-consultant-3821567?jobId=jobstreet-id-job-3821567&sectionRank=2017&token=0~357b46f9-3b28-40ef-b670-614aaa1640ef&fr=SRP%20Job%20Listing", "qualified": []}, {"title": "DevOps Engineer", "link": "https://www.jobstreet.co.id/id/job/devops-engineer-3818743?jobId=jobstreet-id-job-3818743&sectionRank=2018&token=0~357b46f9-3b28-40ef-b670-614aaa1640ef&fr=SRP%20Job%20Listing", "qualified": []}, {"title": "SAP ABAP Consultant", "link": "https://www.jobstreet.co.id/id/job/sap-abap-consultant-3840336?jobId=jobstreet-id-job-3840336&sectionRank=2019&token=0~357b46f9-3b28-40ef-b670-614aaa1640ef&fr=SRP%20Job%20Listing", "qualified": []}, {"title": "DevOps Application Support (Azure)", "link": "https://www.jobstreet.co.id/id/job/devops-application-support-azure-3817528?jobId=jobstreet-id-job-3817528&sectionRank=2020&token=0~357b46f9-3b28-40ef-b670-614aaa1640ef&fr=SRP%20Job%20Listing", "qualified": []}, {"title": "Senior System Analyst", "link": "https://www.jobstreet.co.id/id/job/senior-system-analyst-3835632?jobId=jobstreet-id-job-3835632&sectionRank=2021&token=0~357b46f9-3b28-40ef-b670-614aaa1640ef&fr=SRP%20Job%20Listing", "qualified": []}, {"title": "Sales Data Analyst (6 months contract)", "link": "https://www.jobstreet.co.id/id/job/sales-data-analyst-6-months-contract-3834503?jobId=jobstreet-id-job-3834503&sectionRank=2022&token=0~357b46f9-3b28-40ef-b670-614aaa1640ef&fr=SRP%20Job%20Listing", "qualified": []}, {"title": "SeaBank - IT Operations Project Manager (Maintenance)", "link": "https://www.jobstreet.co.id/id/job/seabank-it-operations-project-manager-maintenance-3832213?jobId=jobstreet-id-job-3832213&sectionRank=2023&token=0~357b46f9-3b28-40ef-b670-614aaa1640ef&fr=SRP%20Job%20Listing", "qualified": []}, {"title": "Mobile Apps Developer", "link": "https://www.jobstreet.co.id/id/job/mobile-apps-developer-3819250?jobId=jobstreet-id-job-3819250&sectionRank=2024&token=0~357b46f9-3b28-40ef-b670-614aaa1640ef&fr=SRP%20Job%20Listing", "qualified": []}, {"title": "SAP PM Consultant", "link": "https://www.jobstreet.co.id/id/job/sap-pm-consultant-3820514?jobId=jobstreet-id-job-3820514&sectionRank=2025&token=0~357b46f9-3b28-40ef-b670-614aaa1640ef&fr=SRP%20Job%20Listing", "qualified": []}, {"title": "Project Support Officer", "link": "https://www.jobstreet.co.id/id/job/project-support-officer-3825005?jobId=jobstreet-id-job-3825005&sectionRank=2026&token=0~357b46f9-3b28-40ef-b670-614aaa1640ef&fr=SRP%20Job%20Listing", "qualified": []}, {"title": "Data Analyst", "link": "https://www.jobstreet.co.id/id/job/data-analyst-3834261?jobId=jobstreet-id-job-3834261&sectionRank=2027&token=0~357b46f9-3b28-40ef-b670-614aaa1640ef&fr=SRP%20Job%20Listing", "qualified": []}, {"title": "IT Developer", "link": "https://www.jobstreet.co.id/id/job/it-developer-3814502?jobId=jobstreet-id-job-3814502&sectionRank=2028&token=0~357b46f9-3b28-40ef-b670-614aaa1640ef&fr=SRP%20Job%20Listing", "qualified": []}, {"title": "Cloud Systems Engineer", "link": "https://www.jobstreet.co.id/id/job/cloud-systems-engineer-3836467?jobId=jobstreet-id-job-3836467&sectionRank=2029&token=0~357b46f9-3b28-40ef-b670-614aaa1640ef&fr=SRP%20Job%20Listing", "qualified": []}, {"title": "Android Developer", "link": "https://www.jobstreet.co.id/id/job/android-developer-3838399?jobId=jobstreet-id-job-3838399&sectionRank=2030&token=0~357b46f9-3b28-40ef-b670-614aaa1640ef&fr=SRP%20Job%20Listing", "qualified": []}, {"title": "Senior QA Engineer", "link": "https://www.jobstreet.co.id/id/job/senior-qa-engineer-3836523?jobId=jobstreet-id-job-3836523&sectionRank=2031&token=0~357b46f9-3b28-40ef-b670-614aaa1640ef&fr=SRP%20Job%20Listing", "qualified": []}, {"title": "Junior Developer", "link": "https://www.jobstreet.co.id/id/job/junior-developer-3835662?jobId=jobstreet-id-job-3835662&sectionRank=2032&token=0~357b46f9-3b28-40ef-b670-614aaa1640ef&fr=SRP%20Job%20Listing", "qualified": []}, {"title": "Pelatihan O Level Fullstack Engineer (Fresh Graduated)", "link": "https://www.jobstreet.co.id/id/job/pelatihan-o-level-fullstack-engineer-fresh-graduated-3834639?jobId=jobstreet-id-job-3834639&sectionRank=2033&token=0~357b46f9-3b28-40ef-b670-614aaa1640ef&fr=SRP%20Job%20Listing", "qualified": []}, {"title": "Cloud Technical SME", "link": "https://www.jobstreet.co.id/id/job/cloud-technical-sme-3835050?jobId=jobstreet-id-job-3835050&sectionRank=2034&token=0~357b46f9-3b28-40ef-b670-614aaa1640ef&fr=SRP%20Job%20Listing", "qualified": []}, {"title": "IT & DATA PROCESSING", "link": "https://www.jobstreet.co.id/id/job/it-data-processing-3831358?jobId=jobstreet-id-job-3831358&sectionRank=2035&token=0~357b46f9-3b28-40ef-b670-614aaa1640ef&fr=SRP%20Job%20Listing", "qualified": []}, {"title": "Senior IoT and 5G Product Management", "link": "https://www.jobstreet.co.id/id/job/senior-iot-and-5g-product-management-3818674?jobId=jobstreet-id-job-3818674&sectionRank=2036&token=0~357b46f9-3b28-40ef-b670-614aaa1640ef&fr=SRP%20Job%20Listing", "qualified": []}, {"title": "Ruby on Rails Developers", "link": "https://www.jobstreet.co.id/id/job/ruby-on-rails-developers-3822329?jobId=jobstreet-id-job-3822329&sectionRank=2037&token=0~357b46f9-3b28-40ef-b670-614aaa1640ef&fr=SRP%20Job%20Listing", "qualified": []}, {"title": "Senior/Software Engineer (Backend, Java)", "link": "https://www.jobstreet.co.id/id/job/senior-software-engineer-backend-java-9331327/origin/sg?jobId=jobstreet-sg-job-9331327&sectionRank=2038&token=0~357b46f9-3b28-40ef-b670-614aaa1640ef&fr=SRP%20Job%20Listing", "qualified": []}, {"title": "Flutter Developer", "link": "https://www.jobstreet.co.id/id/job/flutter-developer-3836554?jobId=jobstreet-id-job-3836554&sectionRank=2039&token=0~357b46f9-3b28-40ef-b670-614aaa1640ef&fr=SRP%20Job%20Listing", "qualified": []}, {"title": "SYSTEMS DEVELOPER", "link": "https://www.jobstreet.co.id/id/job/systems-developer-3817496?jobId=jobstreet-id-job-3817496&sectionRank=2040&token=0~357b46f9-3b28-40ef-b670-614aaa1640ef&fr=SRP%20Job%20Listing", "qualified": []}]